sketchbook/__init__.py
sketchbook/__init__.pyi
sketchbook/py.typed
sketchbook/sketchbook.cpython-314-i386-linux-gnu.so
sketchbook_py-1.0.0.dist-info/METADATA
sketchbook_py-1.0.0.dist-info/WHEEL
sketchbook_py-1.0.0.dist-info/RECORD
