Metadata-Version: 2.4
Name: sketchbook-py
Version: 1.0.0
Classifier: Programming Language :: Rust
Classifier: Programming Language :: Python :: Implementation :: CPython
Summary: A Python wrapper for the Sketchbook API, providing easy access to its features and functionalities.
Author-email: Mythos_404 <mythos_404@outlook.com>
Requires-Python: >=3.10
